metaflow_extensions/kubeflow_pipelines_ext/cmd/mfextinit_kubeflow_pipelines_ext.py
metaflow_extensions/kubeflow_pipelines_ext/config/mfextinit_kubeflow_pipelines_ext.py
metaflow_extensions/kubeflow_pipelines_ext/plugins/mfextinit_kubeflow_pipelines_ext.py
metaflow_extensions/kubeflow_pipelines_ext/plugins/kubeflow_pipelines/__init__.py
metaflow_extensions/kubeflow_pipelines_ext/plugins/kubeflow_pipelines/generate_input_paths.py
metaflow_extensions/kubeflow_pipelines_ext/plugins/kubeflow_pipelines/kubeflow_pipelines.py
metaflow_extensions/kubeflow_pipelines_ext/plugins/kubeflow_pipelines/kubeflow_pipelines_cli.py
metaflow_extensions/kubeflow_pipelines_ext/plugins/kubeflow_pipelines/kubeflow_pipelines_decorator.py
metaflow_extensions/kubeflow_pipelines_ext/plugins/kubeflow_pipelines/kubeflow_pipelines_exceptions.py
metaflow_extensions/kubeflow_pipelines_ext/plugins/kubeflow_pipelines/kubeflow_pipelines_utils.py
metaflow_extensions/kubeflow_pipelines_ext/toplevel/mfextinit_kubeflow_pipelines_ext.py
metaflow_extensions/kubeflow_pipelines_ext/toplevel/toplevel.py
metaflow_kubeflow-0.0.2.dist-info/licenses/LICENSE
metaflow_kubeflow-0.0.2.dist-info/METADATA
metaflow_kubeflow-0.0.2.dist-info/WHEEL
metaflow_kubeflow-0.0.2.dist-info/top_level.txt
metaflow_kubeflow-0.0.2.dist-info/RECORD
